dgtl_pyqldb/__init__.py
dgtl_pyqldb/ledger_helper.py
dgtl_pyqldb-1.0.13.dist-info/METADATA
dgtl_pyqldb-1.0.13.dist-info/WHEEL
dgtl_pyqldb-1.0.13.dist-info/top_level.txt
dgtl_pyqldb-1.0.13.dist-info/RECORD
