Metadata-Version: 2.1
Name: dgtl_pyqldb
Version: 1.0.13
Summary: AWS DynamoDB python wrapper with backward compatibility
Author: Olivier Witteman
License: MIT
Requires-Dist: boto3
Requires-Dist: pandas
Requires-Dist: uuid
